radstract/__init__.py
radstract/testdata.py
radstract/analysis/__init__.py
radstract/analysis/shapedistro/__init__.py
radstract/analysis/shapedistro/plots.py
radstract/analysis/shapedistro/models/README.md
radstract/analysis/shapedistro/models/__init__.py
radstract/analysis/shapedistro/models/a3.py
radstract/analysis/shapedistro/models/common.py
radstract/analysis/shapedistro/models/d2.py
radstract/data/__init__.py
radstract/data/colors.py
radstract/data/models.py
radstract/data/multimodal.py
radstract/data/dicom/__init__.py
radstract/data/dicom/exports.py
radstract/data/dicom/main.py
radstract/data/dicom/utils.py
radstract/data/dicom/validator.py
radstract/data/images/__init__.py
radstract/data/images/filters.py
radstract/data/images/utils.py
radstract/data/nifti/__init__.py
radstract/data/nifti/main.py
radstract/datasets/__init__.py
radstract/datasets/huggingface.py
radstract/datasets/nnunet.py
radstract/datasets/polygon.py
radstract/datasets/polygon_utils.py
radstract/datasets/utils.py
radstract/math/__init__.py
radstract/math/main.py
radstract/visuals/__init__.py
radstract/visuals/report_generator.py
radstract/visuals/report_utils.py
radstract-1.0.0.dist-info/METADATA
radstract-1.0.0.dist-info/WHEEL
radstract-1.0.0.dist-info/licenses/LICENSE
radstract-1.0.0.dist-info/RECORD
