Metadata-Version: 2.4
Name: radstract
Version: 1.0.0
Author-email: Sharpz7 <adam.mcarthur62@gmail.com>
License: Apache-2.0
License-File: LICENSE
Requires-Python: <4.0,>=3.10
Requires-Dist: black>=25.1.0
Requires-Dist: importlib-metadata>=7.1.0
Requires-Dist: licensecheck>=2023.5.2
Requires-Dist: matplotlib>=3.8.2
Requires-Dist: nibabel==5.2.1
Requires-Dist: numpy==1.26.4
Requires-Dist: opencv-python>=4.9.0.80
Requires-Dist: pdoc>=14.4.0
Requires-Dist: pillow>=11.0.0
Requires-Dist: pydicom>=3.0.1
Requires-Dist: pylibjpeg-openjpeg>=2.2.1
Requires-Dist: pylibjpeg>=2.0.1
Requires-Dist: pytest-cov>=5.0.0
Requires-Dist: pytest-mock>=3.14.0
Requires-Dist: pytest-xdist>=3.6.1
Requires-Dist: pytest>=8.1.1
Requires-Dist: scikit-image>=0.24.0
Requires-Dist: simpleitk>=2.4.0
Requires-Dist: sympy>=1.12
Requires-Dist: trimesh>=4.0.5
Requires-Dist: vulture>=2.11
Requires-Dist: weasyprint>=65.1
